binney/__init__.py
binney/binney.abi3.so
pybinney-0.2.2.dist-info/METADATA
pybinney-0.2.2.dist-info/WHEEL
pybinney-0.2.2.dist-info/entry_points.txt
pybinney-0.2.2.dist-info/RECORD
