Metadata-Version: 2.4
Name: pybinney
Version: 0.2.2
Classifier: Programming Language :: Python
Classifier: Programming Language :: Rust
Requires-Dist: polars-u64-idx[pyarrow]>=1.6.0 ; extra == 'polars'
Requires-Dist: numpy>=1.26 ; extra == 'polars'
Provides-Extra: polars
Requires-Python: ~=3.9
